[{"area_id":39.0,"name":"4-1","lat":35.646543,"long":139.667379,"status":0.0,"note":"○"},{"area_id":39.0,"name":"4-2","lat":35.65097,"long":139.668648,"status":0.0,"note":"○"},{"area_id":39.0,"name":"4-3","lat":35.649148,"long":139.665971,"status":0.0,"note":"○"},{"area_id":39.0,"name":"4-4","lat":35.649343,"long":139.671896,"status":0.0,"note":"○"},{"area_id":39.0,"name":"4-5","lat":35.647252,"long":139.665442,"status":0.0,"note":"○"},{"area_id":39.0,"name":"4-6","lat":35.650645,"long":139.668405,"status":0.0,"note":"○"},{"area_id":39.0,"name":"4-7","lat":35.645971,"long":139.667277,"status":0.0,"note":"○"},{"area_id":39.0,"name":"4-8","lat":35.650963,"long":139.669321,"status":0.0,"note":"○"},{"area_id":39.0,"name":"5-1","lat":35.646571,"long":139.674261,"status":0.0,"note":"○"},{"area_id":39.0,"name":"5-2","lat":35.643706,"long":139.666191,"status":0.0,"note":"○"},{"area_id":39.0,"name":"5-3","lat":35.644987,"long":139.671123,"status":0.0,"note":"○"},{"area_id":39.0,"name":"5-4","lat":35.645388,"long":139.667829,"status":0.0,"note":"○"},{"area_id":39.0,"name":"5-5","lat":35.647404,"long":139.671402,"status":0.0,"note":"○"},{"area_id":39.0,"name":"5-6","lat":35.645216,"long":139.671931,"status":0.0,"note":"○"},{"area_id":39.0,"name":"5-7","lat":35.6459215,"long":139.6740403,"status":0.0,"note":"○"},{"area_id":39.0,"name":"5-8","lat":35.6481035,"long":139.6720572,"status":0.0,"note":"○"},{"area_id":39.0,"name":"6-1","lat":35.643294,"long":139.673022,"status":0.0,"note":"○"},{"area_id":39.0,"name":"6-4","lat":35.645363,"long":139.678813,"status":0.0,"note":"○"},{"area_id":39.0,"name":"6-7","lat":35.642328,"long":139.674069,"status":0.0,"note":"○"},{"area_id":39.0,"name":"6-8","lat":35.64378,"long":139.67355,"status":0.0,"note":"○"},{"area_id":41.0,"name":"10-2","lat":35.654874,"long":139.658649,"status":0.0,"note":"○"},{"area_id":41.0,"name":"10-3","lat":35.654715,"long":139.657268,"status":0.0,"note":"○"},{"area_id":41.0,"name":"19-1","lat":35.653154,"long":139.662256,"status":0.0,"note":"○"},{"area_id":41.0,"name":"19-2","lat":35.651909,"long":139.660887,"status":0.0,"note":"△"},{"area_id":41.0,"name":"19-3","lat":35.6533589,"long":139.6620263,"status":0.0,"note":"○"},{"area_id":41.0,"name":"19-4","lat":35.654865,"long":139.6608647,"status":0.0,"note":"○"},{"area_id":41.0,"name":"19-5","lat":35.6519994,"long":139.6624175,"status":0.0,"note":"○"},{"area_id":41.0,"name":"19-6","lat":35.6517007,"long":139.6621896,"status":0.0,"note":"○"},{"area_id":41.0,"name":"19-7","lat":35.6526901,"long":139.6607043,"status":0.0,"note":"○"},{"area_id":40.0,"name":"27-1","lat":35.6537812,"long":139.6710156,"status":0.0,"note":"○"},{"area_id":40.0,"name":"27-2","lat":35.657501,"long":139.668188,"status":0.0,"note":"○"},{"area_id":40.0,"name":"27-3","lat":35.655725,"long":139.669672,"status":0.0,"note":"○"},{"area_id":40.0,"name":"27-4","lat":35.654693,"long":139.668286,"status":0.0,"note":"○"},{"area_id":40.0,"name":"27-5","lat":35.6538802,"long":139.6717978,"status":0.0,"note":"○"},{"area_id":40.0,"name":"27-6","lat":35.654813,"long":139.6656139,"status":0.0,"note":"×"},{"area_id":40.0,"name":"27-7","lat":35.654843,"long":139.667257,"status":0.0,"note":"○"},{"area_id":40.0,"name":"27-8","lat":35.6552266,"long":139.667801,"status":0.0,"note":"○"},{"area_id":40.0,"name":"28-1","lat":35.656734,"long":139.678216,"status":0.0,"note":"○"},{"area_id":40.0,"name":"28-2","lat":35.656824,"long":139.676529,"status":0.0,"note":"○"},{"area_id":40.0,"name":"28-3","lat":35.657183,"long":139.678157,"status":0.0,"note":"○"},{"area_id":40.0,"name":"28-4","lat":35.655879,"long":139.676989,"status":0.0,"note":"○"},{"area_id":40.0,"name":"28-5","lat":35.655548,"long":139.676261,"status":0.0,"note":"○"},{"area_id":40.0,"name":"28-6","lat":35.659739,"long":139.676652,"status":0.0,"note":"○"},{"area_id":40.0,"name":"28-7","lat":35.656472,"long":139.676873,"status":0.0,"note":"○"},{"area_id":40.0,"name":"29-1","lat":35.6599044,"long":139.6692198,"status":0.0,"note":"○"},{"area_id":40.0,"name":"29-2","lat":35.65942,"long":139.6735946,"status":0.0,"note":"×"},{"area_id":40.0,"name":"29-3","lat":35.659187,"long":139.673729,"status":0.0,"note":"○"},{"area_id":40.0,"name":"29-4","lat":35.6599006,"long":139.6759288,"status":0.0,"note":"×"},{"area_id":40.0,"name":"29-5","lat":35.658872,"long":139.668761,"status":0.0,"note":"○"},{"area_id":40.0,"name":"29-6","lat":35.6580599,"long":139.6685197,"status":0.0,"note":"○"},{"area_id":40.0,"name":"29-7","lat":35.657821,"long":139.673359,"status":0.0,"note":"○"},{"area_id":41.0,"name":"30-1","lat":35.659964,"long":139.664457,"status":0.0,"note":"×"},{"area_id":41.0,"name":"30-2","lat":35.6598041,"long":139.6620608,"status":0.0,"note":"×"},{"area_id":41.0,"name":"30-3","lat":35.661851,"long":139.663307,"status":0.0,"note":"○"},{"area_id":41.0,"name":"30-4","lat":35.6584601,"long":139.6611379,"status":0.0,"note":"○"},{"area_id":41.0,"name":"30-5","lat":35.659813,"long":139.66438,"status":0.0,"note":"×"},{"area_id":41.0,"name":"30-6","lat":35.661464,"long":139.665249,"status":0.0,"note":"○"},{"area_id":41.0,"name":"30-7","lat":35.661658,"long":139.665298,"status":0.0,"note":"○"},{"area_id":41.0,"name":"31-1","lat":35.661279,"long":139.658218,"status":0.0,"note":"○"},{"area_id":41.0,"name":"31-2","lat":35.660102,"long":139.6553,"status":0.0,"note":"○"},{"area_id":41.0,"name":"31-3","lat":35.659472,"long":139.656403,"status":0.0,"note":"○"},{"area_id":41.0,"name":"31-4","lat":35.658154,"long":139.658066,"status":0.0,"note":"○"},{"area_id":41.0,"name":"31-5","lat":35.657685,"long":139.658814,"status":0.0,"note":"○"},{"area_id":41.0,"name":"31-6","lat":35.659496,"long":139.657989,"status":0.0,"note":"○"},{"area_id":41.0,"name":"31-7","lat":35.656995,"long":139.659691,"status":0.0,"note":"○"},{"area_id":42.0,"name":"32-1","lat":35.6692683,"long":139.6563181,"status":0.0,"note":"○"},{"area_id":42.0,"name":"32-2","lat":35.668584,"long":139.655983,"status":0.0,"note":"○"},{"area_id":42.0,"name":"32-7","lat":35.6681094,"long":139.6566632,"status":0.0,"note":"○"},{"area_id":42.0,"name":"32-8","lat":35.670509,"long":139.660683,"status":0.0,"note":"○"},{"area_id":41.0,"name":"33-1","lat":35.66313,"long":139.66082,"status":0.0,"note":"○"},{"area_id":42.0,"name":"33-2","lat":35.670579,"long":139.661896,"status":0.0,"note":"○"},{"area_id":42.0,"name":"33-3","lat":35.667025,"long":139.66442,"status":0.0,"note":"○"},{"area_id":42.0,"name":"33-4","lat":35.666312,"long":139.66398,"status":0.0,"note":"○"},{"area_id":41.0,"name":"33-5","lat":35.664612,"long":139.66538,"status":0.0,"note":"○"},{"area_id":41.0,"name":"33-6","lat":35.66551,"long":139.662935,"status":0.0,"note":"○"},{"area_id":42.0,"name":"33-7","lat":35.671234,"long":139.663116,"status":0.0,"note":"○"},{"area_id":41.0,"name":"33-8","lat":35.665658,"long":139.661717,"status":0.0,"note":"○"},{"area_id":35.0,"name":"40-2","lat":35.665012,"long":139.637631,"status":0.0,"note":"○"},{"area_id":35.0,"name":"40-5","lat":35.6647831,"long":139.6389093,"status":0.0,"note":"○"},{"area_id":35.0,"name":"40-7","lat":35.665148,"long":139.640028,"status":0.0,"note":"○"},{"area_id":35.0,"name":"40-8","lat":35.664121,"long":139.636619,"status":0.0,"note":"○"},{"area_id":35.0,"name":"41-1","lat":35.663911,"long":139.63947,"status":0.0,"note":"○"},{"area_id":35.0,"name":"41-4","lat":35.660383,"long":139.641434,"status":0.0,"note":"○"},{"area_id":35.0,"name":"41-6","lat":35.6615902,"long":139.6414628,"status":0.0,"note":"○"},{"area_id":35.0,"name":"41-8","lat":35.661134,"long":139.641844,"status":0.0,"note":"○"},{"area_id":35.0,"name":"42-1","lat":35.658756,"long":139.6439,"status":0.0,"note":"○"},{"area_id":35.0,"name":"42-2","lat":35.659031,"long":139.64625,"status":0.0,"note":"○"},{"area_id":35.0,"name":"42-3","lat":35.6591138,"long":139.6485713,"status":0.0,"note":"×"},{"area_id":35.0,"name":"42-4","lat":35.6581309,"long":139.643696,"status":0.0,"note":"○"},{"area_id":35.0,"name":"42-5","lat":35.658172,"long":139.646746,"status":0.0,"note":"○"},{"area_id":35.0,"name":"42-6","lat":35.659443,"long":139.648474,"status":0.0,"note":"○"},{"area_id":35.0,"name":"43-1","lat":35.65765,"long":139.642026,"status":0.0,"note":"×"},{"area_id":35.0,"name":"43-2","lat":35.653821,"long":139.643089,"status":0.0,"note":"○"},{"area_id":35.0,"name":"43-3","lat":35.654922,"long":139.637799,"status":0.0,"note":"○"},{"area_id":35.0,"name":"43-4","lat":35.657398,"long":139.638025,"status":0.0,"note":"×"},{"area_id":35.0,"name":"43-5","lat":35.659178,"long":139.63953,"status":0.0,"note":"○"},{"area_id":35.0,"name":"43-6","lat":35.656171,"long":139.636531,"status":0.0,"note":"○"},{"area_id":35.0,"name":"43-7","lat":35.659093,"long":139.636445,"status":0.0,"note":"○"},{"area_id":35.0,"name":"43-8","lat":35.655429,"long":139.637826,"status":0.0,"note":"○"},{"area_id":37.0,"name":"50-1","lat":35.656214,"long":139.618906,"status":0.0,"note":"○"},{"area_id":37.0,"name":"50-2","lat":35.655831,"long":139.622773,"status":0.0,"note":"○"},{"area_id":37.0,"name":"50-3","lat":35.6581721,"long":139.6185949,"status":0.0,"note":"○"},{"area_id":37.0,"name":"50-4","lat":35.657341,"long":139.619585,"status":0.0,"note":"○"},{"area_id":37.0,"name":"50-5","lat":35.656666,"long":139.6219544,"status":0.0,"note":"○"},{"area_id":37.0,"name":"50-6","lat":35.6557323,"long":139.6197426,"status":0.0,"note":"○"},{"area_id":37.0,"name":"50-7","lat":35.655022,"long":139.622822,"status":0.0,"note":"○"},{"area_id":37.0,"name":"50-8","lat":35.6575811,"long":139.6228698,"status":0.0,"note":"○"},{"area_id":37.0,"name":"51-1","lat":35.6524264,"long":139.6236373,"status":0.0,"note":"○"},{"area_id":37.0,"name":"51-2","lat":35.656009,"long":139.629138,"status":0.0,"note":"○"},{"area_id":37.0,"name":"51-3","lat":35.648866,"long":139.623341,"status":0.0,"note":"○"},{"area_id":37.0,"name":"51-4","lat":35.654551,"long":139.627384,"status":0.0,"note":"○"},{"area_id":37.0,"name":"51-5","lat":35.655071,"long":139.625309,"status":0.0,"note":"○"},{"area_id":37.0,"name":"51-6","lat":35.651667,"long":139.624867,"status":0.0,"note":"○"},{"area_id":37.0,"name":"51-7","lat":35.6490808,"long":139.6250326,"status":0.0,"note":"○"},{"area_id":37.0,"name":"51-8","lat":35.652409,"long":139.626101,"status":0.0,"note":"○"},{"area_id":37.0,"name":"52-1","lat":35.652546,"long":139.61684,"status":0.0,"note":"○"},{"area_id":37.0,"name":"52-2","lat":35.650607,"long":139.619411,"status":0.0,"note":"○"},{"area_id":37.0,"name":"52-3","lat":35.658527,"long":139.618522,"status":0.0,"note":"△"},{"area_id":37.0,"name":"52-4","lat":35.659304,"long":139.616775,"status":0.0,"note":"○"},{"area_id":37.0,"name":"52-5","lat":35.652563,"long":139.61751,"status":0.0,"note":"○"},{"area_id":37.0,"name":"52-6","lat":35.656983,"long":139.615508,"status":0.0,"note":"○"},{"area_id":37.0,"name":"52-7","lat":35.651046,"long":139.619601,"status":0.0,"note":"○"},{"area_id":37.0,"name":"52-8","lat":35.658436,"long":139.617103,"status":0.0,"note":"○"},{"area_id":36.0,"name":"53-2","lat":35.658482,"long":139.613126,"status":0.0,"note":"○"},{"area_id":36.0,"name":"53-4","lat":35.659216,"long":139.613512,"status":0.0,"note":"○"},{"area_id":36.0,"name":"53-5","lat":35.6543,"long":139.614309,"status":0.0,"note":"○"},{"area_id":36.0,"name":"53-6","lat":35.653755,"long":139.612863,"status":0.0,"note":"○"},{"area_id":36.0,"name":"53-7","lat":35.651871,"long":139.614186,"status":0.0,"note":"○"},{"area_id":36.0,"name":"53-8","lat":35.656036,"long":139.614229,"status":0.0,"note":"○"},{"area_id":36.0,"name":"54-1","lat":35.656048,"long":139.607256,"status":0.0,"note":"○"},{"area_id":38.0,"name":"54-2","lat":35.655368,"long":139.607653,"status":0.0,"note":"○"},{"area_id":36.0,"name":"54-3","lat":35.6583023,"long":139.6066432,"status":0.0,"note":"○"},{"area_id":36.0,"name":"54-4","lat":35.656994,"long":139.605088,"status":0.0,"note":"○"},{"area_id":36.0,"name":"54-5","lat":35.658614,"long":139.60649,"status":0.0,"note":"○"},{"area_id":36.0,"name":"54-6","lat":35.658422,"long":139.603913,"status":0.0,"note":"○"},{"area_id":38.0,"name":"54-8","lat":35.657649,"long":139.603628,"status":0.0,"note":"○"},{"area_id":36.0,"name":"55-1","lat":35.6520766,"long":139.612318,"status":0.0,"note":"○"},{"area_id":36.0,"name":"55-2","lat":35.649734,"long":139.613252,"status":0.0,"note":"○"},{"area_id":38.0,"name":"55-3","lat":35.649414,"long":139.610572,"status":0.0,"note":"○"},{"area_id":38.0,"name":"55-4","lat":35.649327,"long":139.609049,"status":0.0,"note":"○"},{"area_id":38.0,"name":"55-5","lat":35.6493205,"long":139.6083754,"status":0.0,"note":"○"},{"area_id":38.0,"name":"55-6","lat":35.6481354,"long":139.6096737,"status":0.0,"note":"○"},{"area_id":38.0,"name":"55-7","lat":35.647321,"long":139.610863,"status":0.0,"note":"○"},{"area_id":36.0,"name":"56-1","lat":35.6452844,"long":139.6160932,"status":0.0,"note":"○"},{"area_id":38.0,"name":"56-2","lat":35.648099,"long":139.612364,"status":0.0,"note":"○"},{"area_id":36.0,"name":"56-3","lat":35.6466901,"long":139.6168687,"status":0.0,"note":"○"},{"area_id":36.0,"name":"56-4","lat":35.646023,"long":139.615954,"status":0.0,"note":"○"},{"area_id":38.0,"name":"56-5","lat":35.64567,"long":139.608828,"status":0.0,"note":"○"},{"area_id":38.0,"name":"56-6","lat":35.647153,"long":139.612669,"status":0.0,"note":"○"},{"area_id":38.0,"name":"56-7","lat":35.6435696,"long":139.6103698,"status":0.0,"note":"○"},{"area_id":36.0,"name":"56-8","lat":35.6486963,"long":139.6150978,"status":0.0,"note":"○"},{"area_id":38.0,"name":"57-1","lat":35.653919,"long":139.608691,"status":0.0,"note":"○"},{"area_id":38.0,"name":"57-2","lat":35.649252,"long":139.602761,"status":0.0,"note":"○"},{"area_id":38.0,"name":"57-3","lat":35.64608,"long":139.60346,"status":0.0,"note":"○"},{"area_id":38.0,"name":"57-4","lat":35.644796,"long":139.603798,"status":0.0,"note":"○"},{"area_id":38.0,"name":"57-5","lat":35.648255,"long":139.607312,"status":0.0,"note":"○"},{"area_id":38.0,"name":"57-6","lat":35.644912,"long":139.60482,"status":0.0,"note":"○"},{"area_id":38.0,"name":"57-7","lat":35.646198,"long":139.601939,"status":0.0,"note":"○"},{"area_id":38.0,"name":"57-8","lat":35.649941,"long":139.606087,"status":0.0,"note":"○"},{"area_id":34.0,"name":"58-1","lat":35.638573,"long":139.59994,"status":0.0,"note":"○"},{"area_id":34.0,"name":"58-2","lat":35.636989,"long":139.596631,"status":0.0,"note":"○"},{"area_id":34.0,"name":"58-3","lat":35.63524,"long":139.601817,"status":0.0,"note":"○"},{"area_id":34.0,"name":"58-4","lat":35.635743,"long":139.598721,"status":0.0,"note":"○"},{"area_id":34.0,"name":"58-5","lat":35.6342406,"long":139.5976677,"status":0.0,"note":"○"},{"area_id":34.0,"name":"58-6","lat":35.634982,"long":139.599685,"status":0.0,"note":"○"},{"area_id":34.0,"name":"58-7","lat":35.6337401,"long":139.5977745,"status":0.0,"note":"○"},{"area_id":34.0,"name":"58-8","lat":35.6318944,"long":139.6031679,"status":0.0,"note":"○"},{"area_id":34.0,"name":"59-1","lat":35.641875,"long":139.589121,"status":0.0,"note":"○"},{"area_id":38.0,"name":"59-2","lat":35.641439,"long":139.602118,"status":0.0,"note":"△"},{"area_id":34.0,"name":"59-3","lat":35.645049,"long":139.600019,"status":0.0,"note":"○"},{"area_id":34.0,"name":"59-4","lat":35.639663,"long":139.591691,"status":0.0,"note":"○"},{"area_id":34.0,"name":"59-5","lat":35.641453,"long":139.598901,"status":0.0,"note":"○"},{"area_id":34.0,"name":"59-6","lat":35.643904,"long":139.589163,"status":0.0,"note":"○"},{"area_id":34.0,"name":"59-7","lat":35.640898,"long":139.600429,"status":0.0,"note":"○"},{"area_id":38.0,"name":"59-8","lat":35.642483,"long":139.602535,"status":0.0,"note":"○"},{"area_id":34.0,"name":"60-1","lat":35.651701,"long":139.601078,"status":0.0,"note":"○"},{"area_id":34.0,"name":"60-4","lat":35.652068,"long":139.596388,"status":0.0,"note":"○"},{"area_id":34.0,"name":"60-5","lat":35.6518,"long":139.597797,"status":0.0,"note":"○"},{"area_id":34.0,"name":"60-6","lat":35.647863,"long":139.593519,"status":0.0,"note":"○"},{"area_id":34.0,"name":"60-7","lat":35.647414,"long":139.601256,"status":0.0,"note":"○"},{"area_id":34.0,"name":"60-9","lat":35.648799,"long":139.593547,"status":0.0,"note":"○"},{"area_id":43.0,"name":"73-2","lat":35.631847,"long":139.613461,"status":0.0,"note":"○"},{"area_id":43.0,"name":"73-5","lat":35.635105,"long":139.617296,"status":0.0,"note":"○"},{"area_id":43.0,"name":"73-6","lat":35.635024,"long":139.615267,"status":0.0,"note":"○"},{"area_id":43.0,"name":"73-7","lat":35.632622,"long":139.615265,"status":0.0,"note":"○"},{"area_id":43.0,"name":"73-8","lat":35.633873,"long":139.621676,"status":0.0,"note":"○"},{"area_id":43.0,"name":"74-1","lat":35.6278537,"long":139.610637,"status":0.0,"note":"○"},{"area_id":43.0,"name":"74-2","lat":35.62891,"long":139.6108556,"status":0.0,"note":"○"},{"area_id":43.0,"name":"74-3","lat":35.6322196,"long":139.6081983,"status":0.0,"note":"○"},{"area_id":43.0,"name":"74-4","lat":35.628008,"long":139.606769,"status":0.0,"note":"○"},{"area_id":43.0,"name":"74-5","lat":35.628933,"long":139.609145,"status":0.0,"note":"○"},{"area_id":43.0,"name":"74-6","lat":35.629903,"long":139.608048,"status":0.0,"note":"○"},{"area_id":43.0,"name":"74-7","lat":35.629743,"long":139.614773,"status":0.0,"note":"○"},{"area_id":43.0,"name":"76-9","lat":35.6261799,"long":139.6119788,"status":0.0,"note":"○"}]